pylon_cli/__init__.py
pylon_cli/main.py
pylon_cli/script.py
pylon_cli-0.4.1.dist-info/METADATA
pylon_cli-0.4.1.dist-info/WHEEL
pylon_cli-0.4.1.dist-info/entry_points.txt
pylon_cli-0.4.1.dist-info/licenses/LICENSE
pylon_cli-0.4.1.dist-info/RECORD
