Metadata-Version: 2.4
Name: pylon-cli
Version: 0.4.1
Summary: Pylon: Command-Line Improvements
Author-email: Cylix Lee <cylix.lee@outlook.com>
License-File: LICENSE
Requires-Python: >=3.13
Requires-Dist: colorama>=0.4.6
